cloudPackage/__init__.py
cloudPackage-0.1.dist-info/LICENSE.txt
cloudPackage-0.1.dist-info/METADATA
cloudPackage-0.1.dist-info/WHEEL
cloudPackage-0.1.dist-info/top_level.txt
cloudPackage-0.1.dist-info/RECORD
