Metadata-Version: 2.1
Name: cloudPackage
Version: 0.1
Summary: Basic AWS Connection Of Verdis
Author: SARTHAK MEHROTRA
Author-email: i-sarthak@verdis.ai
Classifier: Programming Language :: Python :: 3
Classifier: License :: OSI Approved :: MIT License
Classifier: Operating System :: OS Independent
License-File: LICENSE.txt
